vikinglotto/__init__.py
vikinglotto/__main__.py
vikinglotto-0.0.6.dist-info/licenses/LICENSE
vikinglotto-0.0.6.dist-info/METADATA
vikinglotto-0.0.6.dist-info/WHEEL
vikinglotto-0.0.6.dist-info/entry_points.txt
vikinglotto-0.0.6.dist-info/top_level.txt
vikinglotto-0.0.6.dist-info/RECORD
