Metadata-Version: 2.4
Name: vikinglotto
Version: 0.0.6
Summary: Generate lottery numbers for Vikinglotto and Eurojackpot
Home-page: https://github.com/chaosrun/vikinglotto-generator
Author: Zhaosi Qu
Author-email: pypi@chaos.run
Project-URL: Bug Tracker, https://github.com/chaosrun/vikinglotto-generator/issues
Classifier: Programming Language :: Python :: 3
Classifier: License :: OSI Approved :: GNU General Public License v3 or later (GPLv3+)
Classifier: Operating System :: OS Independent
Requires-Python: >=3.6
License-File: LICENSE
Dynamic: license-file
